main.py
salome_to_python-0.1.0.dist-info/METADATA
salome_to_python-0.1.0.dist-info/WHEEL
salome_to_python-0.1.0.dist-info/entry_points.txt
salome_to_python-0.1.0.dist-info/top_level.txt
salome_to_python-0.1.0.dist-info/RECORD
