Metadata-Version: 2.4
Name: salome-to-python
Version: 0.1.0
Summary: Convert Salomé-Meca MED meshes and Code_Aster .comm files into NumPy-ready Python data.
Author: Louis Remes
License: Proprietary
Keywords: salome,med,code_aster,finite element,meshio
Requires-Python: >=3.10
Requires-Dist: meshio>=5.3.5
Requires-Dist: h5py>=3.15
Requires-Dist: numpy>=1.26
